andotp_decrypt.py
generate_code.py
generate_qr_codes.py
andotp_decrypt-0.1.7.dist-info/entry_points.txt
andotp_decrypt-0.1.7.dist-info/LICENSE
andotp_decrypt-0.1.7.dist-info/WHEEL
andotp_decrypt-0.1.7.dist-info/METADATA
andotp_decrypt-0.1.7.dist-info/RECORD
